msh_engine/__init__.py
msh_engine/core.py
msh_engine/db_utils.py
msh_engine/export.py
msh_engine/generic.py
msh_engine/lifecycle.py
msh_engine/logger.py
msh_engine/metadata.py
msh_engine/snowflake_utils.py
msh_engine/sql_utils.py
msh_engine/validation.py
msh_engine/sources/base.py
msh_engine/sources/rest_api.py
msh_engine/sources/sql_database.py
msh_engine-0.1.1.dist-info/licenses/LICENSE.txt
msh_engine-0.1.1.dist-info/METADATA
msh_engine-0.1.1.dist-info/WHEEL
msh_engine-0.1.1.dist-info/top_level.txt
msh_engine-0.1.1.dist-info/RECORD
