Metadata-Version: 2.4
Name: msh-engine
Version: 0.1.1
Summary: The runtime engine for the msh atomic data platform.
Author-email: Januka Peiris <jaypeiris91@gmail.com>
License: Business Source License 1.1 (BSL 1.1)
Project-URL: Homepage, https://github.com/jay-peiris/dbt-bridge
Project-URL: Repository, https://github.com/jay-peiris/dbt-bridge
Project-URL: Issues, https://github.com/jay-peiris/dbt-bridge/issues
Keywords: dbt,dlt,etl,reverse-etl,data-engineering,duckdb
Classifier: Development Status :: 3 - Alpha
Classifier: Intended Audience :: Developers
Classifier: License :: Other/Proprietary License
Classifier: Programming Language :: Python :: 3
Classifier: Topic :: Database
Classifier: Topic :: Software Development :: Libraries :: Python Modules
Requires-Python: >=3.11
License-File: LICENSE.txt
Requires-Dist: dbt-core>=1.5.0
Requires-Dist: dbt-duckdb>=1.5.0
Requires-Dist: dlt[parquet]>=0.4.0
Requires-Dist: pandas
Requires-Dist: requests
Requires-Dist: pyarrow
Requires-Dist: sqlalchemy>=1.4.0
Provides-Extra: postgres
Requires-Dist: dlt[postgres]; extra == "postgres"
Requires-Dist: psycopg2-binary; extra == "postgres"
Provides-Extra: snowflake
Requires-Dist: dlt[snowflake]; extra == "snowflake"
Requires-Dist: snowflake-sqlalchemy; extra == "snowflake"
Provides-Extra: redshift
Requires-Dist: dlt[redshift]; extra == "redshift"
Requires-Dist: psycopg2-binary; extra == "redshift"
Provides-Extra: bigquery
Requires-Dist: dlt[bigquery]; extra == "bigquery"
Requires-Dist: db-dtypes; extra == "bigquery"
Provides-Extra: duckdb
Requires-Dist: dlt[duckdb]; extra == "duckdb"
Provides-Extra: athena
Requires-Dist: dlt[athena]; extra == "athena"
Provides-Extra: databricks
Requires-Dist: dlt[databricks]; extra == "databricks"
Provides-Extra: mssql
Requires-Dist: dlt[mssql]; extra == "mssql"
Requires-Dist: pyodbc; extra == "mssql"
Provides-Extra: synapse
Requires-Dist: dlt[synapse]; extra == "synapse"
Requires-Dist: pyodbc; extra == "synapse"
Provides-Extra: fabric
Requires-Dist: dlt[mssql]; extra == "fabric"
Requires-Dist: pyodbc; extra == "fabric"
Provides-Extra: trino
Requires-Dist: dlt[trino]; extra == "trino"
Provides-Extra: s3
Requires-Dist: dlt[s3]; extra == "s3"
Provides-Extra: gcs
Requires-Dist: dlt[gs]; extra == "gcs"
Provides-Extra: azure
Requires-Dist: dlt[az]; extra == "azure"
Provides-Extra: filesystem
Requires-Dist: dlt[filesystem]; extra == "filesystem"
Provides-Extra: all
Requires-Dist: dlt[postgres]; extra == "all"
Requires-Dist: psycopg2-binary; extra == "all"
Requires-Dist: dlt[snowflake]; extra == "all"
Requires-Dist: dlt[redshift]; extra == "all"
Requires-Dist: dlt[bigquery]; extra == "all"
Requires-Dist: dlt[duckdb]; extra == "all"
Requires-Dist: dlt[athena]; extra == "all"
Requires-Dist: dlt[databricks]; extra == "all"
Requires-Dist: dlt[mssql]; extra == "all"
Requires-Dist: pyodbc; extra == "all"
Requires-Dist: dlt[synapse]; extra == "all"
Requires-Dist: dlt[trino]; extra == "all"
Requires-Dist: dlt[s3]; extra == "all"
Requires-Dist: dlt[gs]; extra == "all"
Requires-Dist: dlt[az]; extra == "all"
Dynamic: license-file
